errol/__init__.py
errol/config_parser.py
errol/errol_launcher.py
errol/watcher.py
errol/xmpp.py
errol/data/template.xml
errol-2.0.3.dist-info/LICENCE.txt
errol-2.0.3.dist-info/METADATA
errol-2.0.3.dist-info/WHEEL
errol-2.0.3.dist-info/entry_points.txt
errol-2.0.3.dist-info/top_level.txt
errol-2.0.3.dist-info/RECORD
