Metadata-Version: 2.1
Name: errol
Version: 2.0.3
Summary: Errol is a file sender that rely on inotify. It can be used to watch a directory and automatically transfer the new files (or modified ones) with XMPP.
Home-page: https://gitlab.com/jnanar/errol
Author: Arnaud Joset
Author-email: info@agayon.be
License: UNKNOWN
Keywords: xmpp file sharing watchdoc
Platform: UNKNOWN
Classifier: Development Status :: 3 - Alpha
Classifier: Environment :: Console
Classifier: Intended Audience :: Developers
Classifier: Topic :: Internet :: XMPP
Classifier: Topic :: Communications
Classifier: Topic :: Communications :: File Sharing
Classifier: License :: OSI Approved :: GNU General Public License v3 (GPLv3)
Classifier: Programming Language :: Python :: 3 :: Only
Classifier: Operating System :: POSIX :: Linux
Requires-Python: >=3.6
Requires-Dist: watchdog
Requires-Dist: slixmpp
Requires-Dist: hachiko
